[
    {
        "id": "gear_input",
        "center": {
            "x": 34.54012345679011,
            "y": 0.26234567901234485
        },
        "driven_radius": 0.0,
        "driving_radius": 0.0
    },
    {
        "id": "gear_1",
        "center": {
            "x": 30.4289645764201,
            "y": 0.5376844446589278
        },
        "driven_radius": 4.1203687669325175,
        "driving_radius": 3.2962950135460143
    },
    {
        "id": "gear_2",
        "center": {
            "x": 23.079652192484012,
            "y": 1.0298937362545826
        },
        "driven_radius": 4.069481422336995,
        "driving_radius": 3.2555851378695966
    },
    {
        "id": "gear_3",
        "center": {
            "x": 14.98589708477479,
            "y": 1.5719609746294236
        },
        "driven_radius": 4.856301734769127,
        "driving_radius": 3.8850413878153014
    },
    {
        "id": "gear_4",
        "center": {
            "x": 6.710279476353568,
            "y": 2.1262081841317575
        },
        "driven_radius": 4.409115396936991,
        "driving_radius": 3.527292317549593
    },
    {
        "id": "gear_5",
        "center": {
            "x": -1.4885428342341047,
            "y": 2.67531214251482
        },
        "driven_radius": 4.689897131264528,
        "driving_radius": 3.751917705011623
    },
    {
        "id": "gear_6",
        "center": {
            "x": -9.792951699269333,
            "y": 3.2314876037068143
        },
        "driven_radius": 4.571094835007032,
        "driving_radius": 3.656875868005626
    },
    {
        "id": "gear_7",
        "center": {
            "x": -17.99308397211556,
            "y": 3.780679294868354
        },
        "driven_radius": 4.561626477666311,
        "driving_radius": 3.6493011821330494
    },
    {
        "id": "gear_8",
        "center": {
            "x": -26.17503039731953,
            "y": 4.328653015869225
        },
        "driven_radius": 4.5509745756580005,
        "driving_radius": 3.6407796605264005
    }
]